smilevalidation/Console.py
smilevalidation/InvalidTypeList.py
smilevalidation/RuleSchema.py
smilevalidation/Validation.py
smilevalidation/test.py
smilevalidation/rule/BaseRule.py
smilevalidation/rule/BoolRule.py
smilevalidation/rule/ComparisonRule.py
smilevalidation/rule/DateRule.py
smilevalidation/rule/DateTimeRule.py
smilevalidation/rule/FloatRule.py
smilevalidation/rule/IntegerRule.py
smilevalidation/rule/ListRule.py
smilevalidation/rule/MatchRule.py
smilevalidation/rule/NotMatchRule.py
smilevalidation/rule/NumericRule.py
smilevalidation/rule/StringRule.py
smilevalidation/rule/TimeRule.py
smilevalidation/rule/__init__.py
smilevalidation/schema/BaseSchema.py
smilevalidation/schema/BoolSchema.py
smilevalidation/schema/ComparisonSchema.py
smilevalidation/schema/DateSchema.py
smilevalidation/schema/DateTimeSchema.py
smilevalidation/schema/FloatSchema.py
smilevalidation/schema/IntegerSchema.py
smilevalidation/schema/NumericSchema.py
smilevalidation/schema/StringSchema.py
smilevalidation/schema/TimeSchema.py
smilevalidation/schema/TypeSchema.py
smilevalidation/schema/__init__.py
SmileValidation-1.2.10.dist-info/LICENSE.txt
SmileValidation-1.2.10.dist-info/METADATA
SmileValidation-1.2.10.dist-info/WHEEL
SmileValidation-1.2.10.dist-info/top_level.txt
SmileValidation-1.2.10.dist-info/RECORD
