Metadata-Version: 2.1
Name: SmileValidation
Version: 1.2.10
Summary: Python3 Validation in another way
Home-page: https://github.com/sitthykun/smilevalidation
Author: Sitthykun LY
Author-email: ly.sitthykun@gmail.com
License: MIT License
Keywords: smilevalidation,smilevalidator,validation,validator
Platform: All
Classifier: Programming Language :: Python :: 3
Classifier: License :: OSI Approved :: MIT License
Classifier: Operating System :: OS Independent
Requires-Python: >=3.5
License-File: LICENSE.txt
